textual_logging/__init__.py
textual_logging/__main__.py
textual_logging/demo.py
textual_logging/formatter.py
textual_logging/handler.py
textual_logging/py.typed
textual_logging/runner.py
textual_logging/widget.py
textual_logging-0.2.0.dist-info/METADATA
textual_logging-0.2.0.dist-info/WHEEL
textual_logging-0.2.0.dist-info/licenses/LICENSE
textual_logging-0.2.0.dist-info/RECORD
